[
    {
        "bookSourceComment": "API，18\nhttp://www.qqmh.vip/",
        "bookSourceGroup": "漫画",
        "bookSourceName": "🎟️亲亲漫画",
        "bookSourceType": 2,
        "bookSourceUrl": "http://api.acg.gd",
        "bookUrlPattern": "",
        "customOrder": 20009005,
        "enabled": true,
        "enabledCookieJar": false,
        "enabledExplore": true,
        "enabledReview": false,
        "exploreUrl": "[{\"title\":\"地区分类\",\"url\":\"\",\"style\":{\"layout_flexGrow\":1,\"layout_flexBasisPercent\":1}},\n{\"title\":\"大陆\",\"url\":\"/app/comic/index?sort=update&filter=dalu&page={{page}}\",\"style\":{\"layout_flexGrow\":1,\"layout_flexBasisPercent\":0.25}},\n{\"title\":\"日漫\",\"url\":\"/app/comic/index?sort=update&filter=riben&page={{page}}\",\"style\":{\"layout_flexGrow\":1,\"layout_flexBasisPercent\":0.25}},\n{\"title\":\"韩漫\",\"url\":\"/app/comic/index?sort=update&filter=hanguo&page={{page}}\",\"style\":{\"layout_flexGrow\":1,\"layout_flexBasisPercent\":0.25}}]",
        "header": "{\n  \"User-Agent\": \"Mozilla/5.0 (Windows NT 10.0; Win64; x64) AppleWebKit/537.36 (KHTML, like Gecko) Chrome/55.0.2883.87 UBrowser/6.2.4094.1 Safari/537.36\"\n}",
        "lastUpdateTime": 1663941752747,
        "loginUrl": "",
        "respondTime": 1141,
        "ruleBookInfo": {
            "author": "$.data.author",
            "coverUrl": "",
            "init": "",
            "intro": "&nbsp;&nbsp;🔖更新时间：{{java.timeFormat(java.getString('$.data.posted_at')*1000)}}{{'\\n&lrm;\\n'}}{{$..description}}",
            "kind": "$..subjects[*].name",
            "lastChapter": "{{$.data.last_chapter_name}} • {{java.timeFormat(java.getString('$.data.posted_at')*1000)}}\n<js>result.replace(/\\s\\d+:\\d+/,'')</js>\n<js>result.replace(/\\//g,'-')</js>",
            "name": "$.data.name",
            "wordCount": ""
        },
        "ruleContent": {
            "content": "@js:\nheader={\"Referer\":baseUrl};\nheaders={\"headers\":JSON.stringify(header)};\n$=JSON.parse(result);\nimglist=$.data.imageArray;\npath=$.data.path;\nurl='http://mangaimg.huliqun.com:44240/';\nurl=url+path;\nhtml='';\nfor(i in imglist){\nhtml +='<img src=\"'+url+imglist[i]+'\">\\n'\n}\nhtml",
            "imageStyle": "FULL"
        },
        "ruleExplore": {
            "bookList": "",
            "coverUrl": "$.coverUrl@js:\nheader={\"Referer\":baseUrl}\nheaders={\"headers\":JSON.stringify(header)}\nresult=result+','+JSON.stringify(headers)"
        },
        "ruleReview": [],
        "ruleSearch": {
            "author": "$.author",
            "bookList": "$.items.*",
            "bookUrl": "http://api.acg.gd/app/comic/view?id={$.id}",
            "coverUrl": "$.coverUrl##$##,{\"headers\":{\"Referer\":\"https://www.acgqd.com\"}}",
            "intro": "$.description",
            "kind": "{{java.timeFormat(java.getString('$.posted_at')*1000)}}",
            "lastChapter": "{{$.last_chapter_name}} • {{java.timeFormat(java.getString('$.posted_at')*1000)}}\n<js>result.replace(/\\s\\d+:\\d+/,'')</js>\n<js>result.replace(/\\//g,'-')</js>",
            "name": "$.name",
            "wordCount": ""
        },
        "ruleToc": {
            "chapterList": "$..chapterGroup.1.*",
            "chapterName": "$.name",
            "chapterUrl": "http://api.acg.gd/app/chapter/view?id={$.id}",
            "updateTime": "{{java.timeFormat(java.getString('$.updated_at')*1000)}} • {{$.count}}P"
        },
        "searchUrl": "http://api.acg.gd/app/comic/search?keywords={{key}}&page={{page}}&sort=post",
        "weight": 0
    }
]