[
    {
        "bookSourceComment": "",
        "bookSourceName": "笔痴中文",
        "bookSourceType": 0,
        "bookSourceUrl": "https://www.bdxnc.com/",
        "customOrder": 0,
        "enabled": false,
        "enabledExplore": true,
        "lastUpdateTime": 0,
        "ruleBookInfo": {
            "author": "class.block_txt2@tag.a.2@text",
            "coverUrl": "img@src",
            "intro": "class.intro_info@html",
            "lastChapter": "class.block_txt2@tag.a.-1@text",
            "name": "class.block_txt2@h2@text",
            "tocUrl": "text.查看目录@href"
        },
        "ruleContent": {
            "content": "id.nr1@html",
            "nextContentUrl": "text.下一页@href",
            "replaceRegex": "##\\s*.*?本章未完.*\\s*|\\s*.*深夜福利电影.*\\s*"
        },
        "ruleExplore": [],
        "ruleSearch": {
            "author": "tag.a.-1@text",
            "bookList": "class.line",
            "bookUrl": "tag.a.1@href",
            "kind": "tag.a.0@text##\\[|\\]",
            "name": "class.line@tag.a.1@text"
        },
        "ruleToc": {
            "chapterList": "class.chapter@li@a",
            "chapterName": "text",
            "chapterUrl": "href",
            "nextTocUrl": "text.下一页@href"
        },
        "searchUrl": "https://m.bdxnc.com/modules/article/waps.php,{\n\"charset\": \"gbk\",\n\"method\": \"POST\",\n\"body\": \"searchkey={{key}}\",\n\"headers\": {\"User-Agent\": \"\"}\n}",
        "weight": 0
    }
]