[
    {
        "bookSourceGroup": "天域战歌",
        "bookSourceName": "言情中文",
        "bookSourceUrl": "https://m.yqzw5.com",
        "enable": false,
        "httpUserAgent": "",
        "loginUrl": "",
        "ruleBookAuthor": "",
        "ruleBookContent": "id.content@p@html",
        "ruleBookKind": "",
        "ruleBookLastChapter": "class.chapter@tag.li.0@a@text",
        "ruleBookName": "",
        "ruleBookUrlPattern": "",
        "ruleChapterList": "class.chapter@li@a",
        "ruleChapterName": "text#返回书籍封.*",
        "ruleChapterUrl": "text.查看目录@href",
        "ruleChapterUrlNext": "text.下一页@href",
        "ruleContentUrl": "href",
        "ruleContentUrlNext": "text.下一页@href",
        "ruleCoverUrl": "",
        "ruleFindUrl": "总排行榜::http://m.yqzw5.com/top/allvisit/\n总推荐榜::http://m.yqzw5.com/top/allvote/\n总收藏榜::http://m.yqzw5.com/top/goodnum/\n玄幻小说::http://m.yqzw5.com/sort/1_searchPage/\n仙侠小说::http://m.yqzw5.com/sort/2_searchPage/\n都市小说::http://m.yqzw5.com/sort/3_searchPage/\n穿越小说::http://m.yqzw5.com/sort/4_searchPage/\n游戏小说::http://m.yqzw5.com/sort/5_searchPage/\n科幻小说::http://m.yqzw5.com/sort/6_searchPage/\n其他小说::http://m.yqzw5.com/sort/7_searchPage/",
        "ruleIntroduce": "class.intro_info@tag.p.0@text",
        "ruleSearchAuthor": "class.block_txt@tag.a.2@text|class.line@tag.a.1@text|tag.a.2@text",
        "ruleSearchCoverUrl": "",
        "ruleSearchKind": "span@tag.a.0@text",
        "ruleSearchLastChapter": "",
        "ruleSearchList": "class.block|class.cover@p|class.SHsectionThree-middle@p",
        "ruleSearchName": "h2@a@text|class.blue@text|tag.a.1@text",
        "ruleSearchNoteUrl": "class.blue@href|tag.a.1@href",
        "ruleSearchUrl": "https://m.yqzw5.com/search/@searchkey=searchKey",
        "serialNumber": 0,
        "weight": 0
    }
]