[
    {
        "bookSourceComment": "",
        "bookSourceGroup": "",
        "bookSourceName": "八一中文网",
        "bookSourceType": 0,
        "bookSourceUrl": "https://m.zwdu.com##1",
        "bookUrlPattern": "",
        "customOrder": -302219,
        "enabled": true,
        "enabledCookieJar": false,
        "enabledExplore": false,
        "exploreUrl": "全本小说::/quanben/\n玄幻小说::/xuanhuan/\n修真小说::/xianxia/\n都市小说::/dushi/\n历史小说::/lishi/\n网游小说::/wangyou/\n科幻小说::/kehuan/\n竞技小说::/jingji/\n言情小说::/yanqing/\n其他小说::/qita/",
        "header": "",
        "lastUpdateTime": 1653348238783,
        "loginUrl": "",
        "respondTime": 12828,
        "ruleBookInfo": {
            "author": "@css:[property=og:novel:author]@content",
            "coverUrl": "@css:[property=og:image]@content",
            "init": "",
            "intro": "id.info.0@tag.p.2@text&&id.intro.0@tag.p.0@text##最后更新：",
            "kind": "@css:[property= og:novel:category]@content",
            "lastChapter": "@css:[property=og:novel:latest_chapter_name]@content",
            "name": "@css:[property=og:novel:book_name]@content",
            "tocUrl": "",
            "wordCount": "@css:[property=og:novel:status]@content"
        },
        "ruleContent": {
            "content": "id.content.0@html",
            "nextContentUrl": "",
            "sourceRegex": "",
            "webJs": ""
        },
        "ruleExplore": {
            "author": "class.author@text##作者：",
            "bookList": "class.bookbox",
            "bookUrl": "class.iTit@tag.a@href##(.*)##https://www.zwdu.com$1###",
            "coverUrl": "class.bookimg@img@src",
            "intro": "class.intro_line@text##简介：",
            "kind": "",
            "lastChapter": "class.update@tag.a@text",
            "name": "class.iTit@tag.a@text",
            "wordCount": ""
        },
        "ruleSearch": {
            "author": "class.result-game-item-info@tag.p.0@tag.span.1@text",
            "bookList": "class.result-item result-game-item",
            "bookUrl": "class.result-item-title result-game-item-title@tag.a@href",
            "coverUrl": "class.result-game-item-pic@img@src",
            "intro": "class.result-game-item-desc@text",
            "kind": "class.result-game-item-info@tag.p.1@tag.span.1@text",
            "lastChapter": "class.result-game-item-info@tag.p.3@tag.a@text",
            "name": "class.result-item-title result-game-item-title@tag.a@text",
            "wordCount": "class.result-game-item-info@tag.p.2@tag.span.1@text"
        },
        "ruleToc": {
            "chapterList": "id.list@tag.dd",
            "chapterName": "tag.a@text",
            "chapterUrl": "tag.a@href##(.*)##https://www.zwdu.com$1###",
            "isVip": "",
            "nextTocUrl": "",
            "updateTime": ""
        },
        "searchUrl": "https://www.zwdu.com/search.php?keyword={{key}}&page={{page}}",
        "weight": 0
    }
]