[
    {
        "bookSourceGroup": "自制,出版,下载,源仓库,网页源",
        "bookSourceName": "无名图书",
        "bookSourceType": 3,
        "bookSourceUrl": "https://www.book123.info",
        "customOrder": 0,
        "enabled": true,
        "enabledCookieJar": true,
        "enabledExplore": true,
        "exploreUrl": "最近更新::/list/?tag=最近更新\n文学::/list/?tag=文学\n社会文化::/list/?tag=社会文化\n历史::/list/?tag=历史\n经济::/list/?tag=经济\n理工科::/list/?tag=理工科\n政治::/list?tag=政治\n健康::/list?tag=健康\n计算机::/list?tag=计算机\n自然科学::/list?tag=自然科学\n设计::/list?tag=设计\n美食旅行::/list?tag=美食旅行\n思想::/list?tag=思想\n生物::/list?tag=生物\n建筑::/list?tag=建筑\n绘本::/list?tag=绘本\n天文::/list?tag=天文\n查看全部::/list?tag=最近更新",
        "lastUpdateTime": 1686110771954,
        "respondTime": 180000,
        "ruleBookInfo": {
            "author": ".detail_author__V_EVp@a@text",
            "coverUrl": "picture@img@src",
            "downloadUrls": ".detail_btns_wrapper__310mw@a@href",
            "intro": ".detail_book_info__Mv_YW@text",
            "name": "h1@text"
        },
        "ruleContent": [],
        "ruleExplore": [],
        "ruleReview": [],
        "ruleSearch": {
            "author": "p.1@text",
            "bookList": "ul@li",
            "bookUrl": "a@href",
            "checkKeyWord": "剑来",
            "coverUrl": "img@src",
            "intro": "p.-1@text",
            "kind": "0",
            "name": "p.0@text"
        },
        "ruleToc": [],
        "searchUrl": "https://www.book123.info/list?key={{key}}",
        "weight": 0
    }
]