[
    {
        "bookSourceGroup": "置顶搜书",
        "bookSourceName": "丹书铁券(感谢)",
        "bookSourceUrl": "https://www.dstiejuan.com",
        "enable": true,
        "loginUrl": "",
        "ruleBookAuthor": "class.detail@tag.p.0@tag.a.0@text",
        "ruleBookContent": "@css:#content@html",
        "ruleBookInfoInit": "",
        "ruleBookKind": "class.detail@tag.p.0@text&&\nclass.detail@tag.p.3@span@text##.*分类：|字数.*|\\(|\\)",
        "ruleBookLastChapter": "class.detail@tag.p.3@tag.a@text##免费章节 |正文卷 |正文 |VIP章节 ",
        "ruleBookName": "class.detail@h1@text",
        "ruleBookUrlPattern": "https://www.dstiejuan.com/book/\\d+.html",
        "ruleChapterList": "class.read@tag.dl.1@dd",
        "ruleChapterName": "tag.a@text",
        "ruleChapterUrl": "text.阅读目录@href",
        "ruleContentUrl": "tag.a@href",
        "ruleCoverUrl": "class.detail@class.bookimg@img@src",
        "ruleFindList": "",
        "ruleFindUrl": "全部小说::/library/0_0_0_searchPage.html\n玄幻奇幻::/library/0_1_0_searchPage.html\n武侠仙侠::/library/0_2_0_searchPage.html\n都市生活::/library/0_3_0_searchPage.html\n历史军事::/library/0_4_0_searchPage.html\n游戏竞技::/library/0_5_0_searchPage.html\n科幻未来::/library/0_6_0_searchPage.html\n恐怖悬疑::/library/0_7_0_searchPage.html\n二次の元::/library/0_8_0_searchPage.html\n经典网文::/library/0_9_0_searchPage.html\n古代言情::/library/0_10_0_searchPage.html\n现代言情::/library/0_11_0_searchPage.html\n幻想奇缘::/library/0_12_0_searchPage.html\n青春校园::/library/0_13_0_searchPage.html\n网络情缘::/library/0_14_0_searchPage.html\n科幻空间::/library/0_15_0_searchPage.html\n鬼怪灵异::/library/0_16_0_searchPage.html\nN次の元::/library/0_17_0_searchPage.html\n言情美文::/library/0_18_0_searchPage.html\n\n总点击榜::/library/allvisit_0_0_searchPage.html\r\n月点击榜::/library/monthvisit_0_0_searchPage.html\r\n周点击榜::/library/weekvisit_0_0_searchPage.html\r\n日点击榜::/library/dayvisit_0_0_searchPage.html\r\n总推荐榜::/library/allvote_0_0_searchPage.html\n月推荐榜::/library/monthvote_0_0_searchPage.html\r\n总收藏榜::/library/goodnum_0_0_searchPage.html\r\n总字数榜::/library/size_0_0_searchPage.html\r\n最新入库::/library/postdate_0_0_searchPage.html",
        "ruleIntroduce": "class.content@tag.p.0@text",
        "ruleSearchAuthor": "class.author@text",
        "ruleSearchCoverUrl": "img@src",
        "ruleSearchIntroduce": "class.intro@text",
        "ruleSearchKind": "class.layui-badge@text&&\ntag.p.0@tag.a.1@text",
        "ruleSearchLastChapter": "class.chapter@text##最新章节：|免费章节 |正文卷 |正文 |VIP章节 ",
        "ruleSearchList": "class.library@li",
        "ruleSearchName": "class.bookname@text",
        "ruleSearchNoteUrl": "class.bookname@href",
        "ruleSearchUrl": "https://www.dstiejuan.com/search.html@searchkey=searchKey",
        "serialNumber": 0,
        "weight": 0
    }
]